{
	"data":{
		"author":"xiaomeng",
		"cateId":"4F46906C14E7416F9CDB1C60C92729B1",
		"conf":"[\n    {\n        \"uiType\": \"textbox\",\n        \"uiTypeText\": \"文本框\",\n        \"name\": \"visualType\",\n        \"label\": \"插件类型\",\n        \"toolTip\": \"\",\n        \"uiProperty\": {\n            \"minlength\": 0,\n            \"maxlength\": 5000,\n            \"placeholder\": \"请输入\",\n            \"disabled\": false,\n            \"icon\": \"\"\n        },\n        \"default\": \"scatter\",\n        \"hidden\": true\n    },\n    {\n        \"uiType\": \"number\",\n        \"uiTypeText\": \"数字框\",\n        \"name\": \"symbolSize\",\n        \"label\": \"点大小\",\n        \"toolTip\": \"\",\n        \"uiProperty\": {\n            \"min\": 0,\n            \"max\": 999999,\n            \"step\": 1,\n            \"disabled\": false,\n            \"controls\": true,\n            \"controls-position\": \"-\"\n        },\n        \"default\": \"20\"\n    }\n]",
		"createBy":"USER1",
		"createDt":"20200115",
		"delFlag":"0",
		"enable":"1",
		"icon":"SNS",
		"id":"B5CCABF78119495F80E58452D03554E3",
		"name":"散点图",
		"ptype":"1",
		"updateBy":"USER1",
		"updateDt":"20200115",
		"version":"0.1"
	},
	"msg":"交易成功",
	"status":"000000"
}